{
    "data": {
        "currency_symbol": "$",
        "label_invoice": "invoice",
        "label_invoice_to": "invoice to",
        "label_invoice_by": "invoice by",
        "label_due_on": "Due on",
        "label_invoice_for": "invoice for",
        "label_description": "description",
        "label_unit": "unit",
        "label_price": "price ($)",
        "label_amount": "Amount",
        "label_subtotal": "subtotal",
        "label_total": "total",
        "label_vat": "vat",
        "label_invoice_date": "invoice date",
        "label_company_siret": "Company SIRET",
        "label_company_vat_number": "Company VAT N°",
        "label_invoice_number": "invoice number",
        "label_reference_number": "ref N°",
        "label_invoice_due_date": "Due date",
        "company_name": "Trusk",
        "date_format": "MMMM Do, YYYY",
        "client_company_name": "My Company",
        "number": "12345",
        "currency_position_before": true,
        "language": "en",
        "id": "ch_1Blg0sBBh3le1kgVPJTctLkm",
        "object": "charge",
        "amount": 1667,
        "amount_refunded": 0,
        "application": null,
        "application_fee": null,
        "balance_transaction": "txn_1Blg0sBBh3le1kgVARPyc1Y8",
        "captured": true,
        "created": 1516291994,
        "currency": "eur",
        "customer": "cus_C4lbqRwN5kISCo",
        "description": "Payment for order or_1Blg0rBBh3le1kgVYu9IwI1v",
        "destination": null,
        "dispute": null,
        "failure_code": null,
        "failure_message": null,
        "fraud_details": {},
        "invoice": null,
        "livemode": false,
        "metadata": {},
        "on_behalf_of": null,
        "order": {
            "id": "or_1Blg0rBBh3le1kgVYu9IwI1v",
            "object": "order",
            "amount": 1667,
            "amount_returned": null,
            "application": null,
            "application_fee": null,
            "charge": "ch_1Blg0sBBh3le1kgVPJTctLkm",
            "created": 1516291993,
            "currency": "eur",
            "customer": "cus_C4lbqRwN5kISCo",
            "email": "cyrille.estrade@centraliens.net",
            "items": [
                {
                    "object": "order_item",
                    "amount": 1667,
                    "currency": "eur",
                    "description": "Pack découverte",
                    "parent": "PACK_DECOUVERTE_10",
                    "quantity": 1,
                    "type": "sku"
                },
                {
                    "object": "order_item",
                    "amount": 0,
                    "currency": "eur",
                    "description": "Taxes (included)",
                    "parent": null,
                    "quantity": null,
                    "type": "tax"
                },
                {
                    "object": "order_item",
                    "amount": 0,
                    "currency": "eur",
                    "description": "Free shipping",
                    "parent": "ship_free-shipping",
                    "quantity": null,
                    "type": "shipping"
                }
            ],
            "livemode": false,
            "metadata": {},
            "returns": {
                "object": "list",
                "data": [],
                "has_more": false,
                "total_count": 0,
                "url": "/v1/order_returns?order=or_1Blg0rBBh3le1kgVYu9IwI1v"
            },
            "selected_shipping_method": "ship_free-shipping",
            "shipping": null,
            "shipping_methods": [
                {
                    "id": "ship_free-shipping",
                    "amount": 0,
                    "currency": "eur",
                    "delivery_estimate": null,
                    "description": "Free shipping"
                }
            ],
            "status": "paid",
            "status_transitions": {
                "canceled": null,
                "fulfiled": null,
                "paid": 1516291995,
                "returned": null
            },
            "updated": 1516291995
        },
        "outcome": {
            "network_status": "approved_by_network",
            "reason": null,
            "risk_level": "normal",
            "seller_message": "Payment complete.",
            "type": "authorized"
        },
        "paid": true,
        "receipt_email": null,
        "receipt_number": "ER56T67",
        "refunded": false,
        "refunds": {
            "object": "list",
            "data": [],
            "has_more": false,
            "total_count": 0,
            "url": "/v1/charges/ch_1Blg0sBBh3le1kgVPJTctLkm/refunds"
        },
        "review": null,
        "shipping": null,
        "source": {
            "id": "card_1BgcRYBBh3le1kgV3LXyfyOm",
            "object": "card",
            "address_city": null,
            "address_country": null,
            "address_line1": null,
            "address_line1_check": null,
            "address_line2": null,
            "address_state": null,
            "address_zip": null,
            "address_zip_check": null,
            "brand": "Visa",
            "country": "US",
            "customer": "cus_C4lbqRwN5kISCo",
            "cvc_check": null,
            "dynamic_last4": null,
            "exp_month": 1,
            "exp_year": 2020,
            "fingerprint": "Wdi4RPmG8ZNiqyiA",
            "funding": "credit",
            "last4": "4242",
            "metadata": {},
            "name": null,
            "tokenization_method": null
        },
        "source_transfer": null,
        "statement_descriptor": null,
        "status": "succeeded",
        "transfer_group": null,
        "company_address": "14 rue Charles V",
        "company_zipcode": "75004",
        "company_city": "Paris",
        "company_country": "France",
        "company_siret": "146-458-246",
        "company_vat_number": "568-3587-345",
        "company_logo": "/home/VA.COM/lg1/Dev/batman.jpg",
        "color": "#2C75FF",
        "client_company_address": "1 infinite Loop",
        "client_company_zipcode": "95014",
        "client_company_city": "Cupertino, CA",
        "client_company_country": "USA",
        "require": {},
        "css": [
            "/home/VA.COM/lg1/Dev/stripe-pdf-invoice/templates/default/css/style.css",
            "/home/VA.COM/lg1/Dev/stripe-pdf-invoice/templates/default/css/foundation.min.css"
        ]
    },
    "body": "/home/VA.COM/lg1/Dev/stripe-pdf-invoice/templates/default/body.pug"
}